cmsplugin_markdownx/__init__.py
cmsplugin_markdownx/cms_plugins.py
cmsplugin_markdownx/forms.py
cmsplugin_markdownx/models.py
cmsplugin_markdownx/tests.py
cmsplugin_markdownx/migrations/0001_initial.py
cmsplugin_markdownx/migrations/__init__.py
cmsplugin_markdownx/static/cmsplugin_markdownx/codehilite_colorful.css
cmsplugin_markdownx/templates/cmsplugin_markdownx/change_form.html
cmsplugin_markdownx/templates/cmsplugin_markdownx/markdownx.html
cmsplugin_markdownx/templatetags/__init__.py
cmsplugin_markdownx/templatetags/cmsplugin_markdownx.py
cmsplugin_markdownx-0.1.2.dist-info/DESCRIPTION.rst
cmsplugin_markdownx-0.1.2.dist-info/METADATA
cmsplugin_markdownx-0.1.2.dist-info/RECORD
cmsplugin_markdownx-0.1.2.dist-info/WHEEL
cmsplugin_markdownx-0.1.2.dist-info/metadata.json
cmsplugin_markdownx-0.1.2.dist-info/top_level.txt
