Metadata-Version: 2.0
Name: cmsplugin-markdownx
Version: 0.1.2
Summary: A plugin for django-cms that wraps django-markdownx, enabling WYSIWYG editing of markdown fields.
Requires-Dist: Django (<1.11)
Requires-Dist: django-cms (<=3.4.2)
Requires-Dist: django-markdownx (<1.7.2)
Requires-Dist: Markdown (<2.6.8)
Requires-Dist: Pygments (>2.0)
